llm_documentcloud.py
llm_documentcloud-0.1.1.dist-info/licenses/LICENSE
llm_documentcloud-0.1.1.dist-info/METADATA
llm_documentcloud-0.1.1.dist-info/WHEEL
llm_documentcloud-0.1.1.dist-info/entry_points.txt
llm_documentcloud-0.1.1.dist-info/top_level.txt
llm_documentcloud-0.1.1.dist-info/RECORD
