Metadata-Version: 2.4
Name: llm-documentcloud
Version: 0.1.1
Summary: LLM integrations for DocumentCloud
Author: Chris Amico
License-Expression: Apache-2.0
Project-URL: Homepage, https://github.com/eyeseast/llm-documentcloud
Project-URL: Changelog, https://github.com/eyeseast/llm-documentcloud/releases
Project-URL: Issues, https://github.com/eyeseast/llm-documentcloud/issues
Project-URL: CI, https://github.com/eyeseast/llm-documentcloud/actions
Requires-Python: >=3.10
License-File: LICENSE
Requires-Dist: llm
Requires-Dist: python-documentcloud>=4.4.1
Provides-Extra: test
Requires-Dist: pytest; extra == "test"
Dynamic: license-file
